render_engine_youtube_embed/__init__.py
render_engine_youtube_embed/plugins.py
render_engine_youtube_embed/youtube_embed.py
render_engine_youtube_embed-2023.7.2.dist-info/LICENSE
render_engine_youtube_embed-2023.7.2.dist-info/METADATA
render_engine_youtube_embed-2023.7.2.dist-info/WHEEL
render_engine_youtube_embed-2023.7.2.dist-info/top_level.txt
render_engine_youtube_embed-2023.7.2.dist-info/RECORD
