Metadata-Version: 2.1
Name: render-engine-youtube-embed
Version: 2023.7.2
Summary: A Render Engine Plugin for replacing Youtube Links with Embed Links
Project-URL: homepage, https://github.com/kjaymiller/render-engine-youtube-link-embed
Project-URL: repository, https://github.com/kjaymiller/render-engine-youtube-link-embed
License-File: LICENSE
Requires-Dist: render-engine (>=2023.3.1b1)
Provides-Extra: dev
Requires-Dist: pytest ; extra == 'dev'
